mallgroup_python_lib/__init__.py
mallgroup_python_lib/heartbeat.py
mallgroup_python_lib/mongo_db_dao.py
mallgroup_python_lib/redis_dao.py
mallgroup_python_lib-0.0.10.dist-info/LICENCE.txt
mallgroup_python_lib-0.0.10.dist-info/METADATA
mallgroup_python_lib-0.0.10.dist-info/WHEEL
mallgroup_python_lib-0.0.10.dist-info/top_level.txt
mallgroup_python_lib-0.0.10.dist-info/RECORD
