Metadata-Version: 2.1
Name: mallgroup-python-lib
Version: 0.0.10
Summary: Official Mallgroup Library
Home-page: UNKNOWN
Author: Data Engineering Mallgroup
Author-email: dataengineering@mallgroup.com
License: UNKNOWN
Platform: UNKNOWN
Classifier: Programming Language :: Python :: 3
Classifier: Programming Language :: Python :: 3.8
Classifier: License :: OSI Approved :: MIT License
License-File: LICENCE.txt
Provides-Extra: dev
Requires-Dist: pytest ; extra == 'dev'
